Metadata-Version: 2.1
Name: test_code_me
Version: 1.0.0
Summary: Hi Bro Whats up
Author: Farbod Parkhooi
Requires-Dist: numpy
